Metadata-Version: 2.4
Name: openize-markitdown-python
Version: 25.6.1
Summary: A document converter for Word, PDF, Excel, and PowerPoint to Markdown.
Home-page: https://github.com/openize-com/openize-markitdown-python
Author: Openize
Author-email: packages@openize.com
License: MIT
Project-URL: Bug Tracker, https://github.com/openize-com/openize-markitdown-python/issues
Classifier: Programming Language :: Python :: 3
Classifier: Programming Language :: Python :: 3.7
Classifier: Programming Language :: Python :: 3.8
Classifier: Programming Language :: Python :: 3.9
Classifier: Programming Language :: Python :: 3.10
Classifier: License :: OSI Approved :: MIT License
Classifier: Operating System :: OS Independent
Classifier: Topic :: Text Processing :: Markup :: Markdown
Requires-Python: >=3.7
License-File: LICENSE
Requires-Dist: aspose-words>=23.0.0
Requires-Dist: aspose-cells-python>=23.0.0
Requires-Dist: aspose-slides>=23.0.0
Requires-Dist: openai>=1.0.0
Requires-Dist: anthropic>=0.3.11
Requires-Dist: requests>=2.25.0
Dynamic: license-file
